AUTHORS
MANIFEST.in
README.creole
setup.py
django_phpBB3/__init__.py
django_phpBB3/admin.py
django_phpBB3/hashers.py
django_phpBB3/models.py
django_phpBB3/test_settings.py
django_phpBB3/tests.py
django_phpBB3/unsupported_models.py
django_phpBB3/utils.py
django_phpBB3/views.py
django_phpBB3.egg-info/PKG-INFO
django_phpBB3.egg-info/SOURCES.txt
django_phpBB3.egg-info/dependency_links.txt
django_phpBB3.egg-info/not-zip-safe
django_phpBB3.egg-info/requires.txt
django_phpBB3.egg-info/top_level.txt
django_phpBB3/management/__init__.py
django_phpBB3/management/commands/__init__.py
django_phpBB3/management/commands/phpbb2djangobb.py
django_phpBB3_project/README.creole
django_phpBB3_project/__init__.py
django_phpBB3_project/manage.py
django_phpBB3_project/settings.py
django_phpBB3_project/urls.py
django_phpBB3_project/wsgi.py
phpBB2DjangoBB_project/README.creole
phpBB2DjangoBB_project/__init__.py
phpBB2DjangoBB_project/forms.py
phpBB2DjangoBB_project/manage.py
phpBB2DjangoBB_project/search_sites.py
phpBB2DjangoBB_project/settings.py
phpBB2DjangoBB_project/sitemap.py
phpBB2DjangoBB_project/urls.py
phpBB2DjangoBB_project/views.py
phpBB2DjangoBB_project/wsgi.py
phpBB2DjangoBB_project/templates/index.html