Metadata-Version: 1.1
Name: django-phpBB3
Version: 0.3.0
Summary: django database models of phpBB3
Home-page: https://github.com/jedie/django-phpBB3/
Author: Jens Diemer
Author-email: django-phpBB3@jensdiemer.de
License: UNKNOWN
Download-URL: http://pypi.python.org/pypi/django-phpBB3/
Keywords: django,forum,phpBB3,phpBB
Platform: UNKNOWN
Classifier: Development Status :: 4 - Beta
Classifier: Environment :: Web Environment
Classifier: Intended Audience :: Developers
Classifier: License :: OSI Approved :: GNU General Public License (GPL)
Classifier: Programming Language :: Python
Classifier: Framework :: Django
Classifier: Topic :: Database :: Front-Ends
Classifier: Topic :: Documentation
Classifier: Topic :: Internet :: WWW/HTTP :: Dynamic Content
Classifier: Topic :: Internet :: WWW/HTTP :: WSGI :: Application
Classifier: Operating System :: OS Independent
